MainServiceManager/__init__.py
MainServiceManager/__main__.py
MainServiceManager/api.py
MainServiceManager/server.py
MainServiceManager/server_utils.py
mainservicemanager-0.0.12.dist-info/METADATA
mainservicemanager-0.0.12.dist-info/WHEEL
mainservicemanager-0.0.12.dist-info/entry_points.txt
mainservicemanager-0.0.12.dist-info/RECORD
