Metadata-Version: 2.1
Name: MainServiceManager
Version: 0.0.12
Summary: Пользовательская программа для управления сервисами, аналогично systemd
Home-page: https://github.com/MainPlay-TG/MainServiceManager.py
Author: MainPlay TG
Author-email: xbox.roman6666666666@gmail.com
Requires-Python: >=3.8,<4.0
Classifier: Programming Language :: Python :: 3
Classifier: Programming Language :: Python :: 3.8
Classifier: Programming Language :: Python :: 3.9
Classifier: Programming Language :: Python :: 3.10
Classifier: Programming Language :: Python :: 3.11
Classifier: Programming Language :: Python :: 3.12
Requires-Dist: Flask (>=3.0.3,<4.0.0)
Requires-Dist: MainShortcuts (>=1.6.95,<2.0.0)
Requires-Dist: requests (>=2.31.0,<3.0.0)
Project-URL: Repository, https://github.com/MainPlay-TG/MainServiceManager.py
